unctl/__init__.py
unctl/__main__.py
unctl/checks/k8s/__init__.py
unctl/checks/k8s/k8s_cronjob_with_negative_starting_deadline/__init__.py
unctl/checks/k8s/k8s_cronjob_with_negative_starting_deadline/k8s_cronjob_with_negative_starting_deadline.json
unctl/checks/k8s/k8s_cronjob_with_negative_starting_deadline/k8s_cronjob_with_negative_starting_deadline.py
unctl/checks/k8s/k8s_cronjobs_suspended_or_invalid_schedule/__init__.py
unctl/checks/k8s/k8s_cronjobs_suspended_or_invalid_schedule/k8s_cronjobs_suspended_or_invalid_schedule.json
unctl/checks/k8s/k8s_cronjobs_suspended_or_invalid_schedule/k8s_cronjobs_suspended_or_invalid_schedule.py
unctl/checks/k8s/k8s_daemonset_configmap_existence/__init__.py
unctl/checks/k8s/k8s_daemonset_configmap_existence/k8s_daemonset_configmap_existence.json
unctl/checks/k8s/k8s_daemonset_configmap_existence/k8s_daemonset_configmap_existence.py
unctl/checks/k8s/k8s_daemonset_pod_template_validation/__init__.py
unctl/checks/k8s/k8s_daemonset_pod_template_validation/k8s_daemonset_pod_template_validation.json
unctl/checks/k8s/k8s_daemonset_pod_template_validation/k8s_daemonset_pod_template_validation.py
unctl/checks/k8s/k8s_daemonset_secret_existence/__init__.py
unctl/checks/k8s/k8s_daemonset_secret_existence/k8s_daemonset_secret_existence.json
unctl/checks/k8s/k8s_daemonset_secret_existence/k8s_daemonset_secret_existence.py
unctl/checks/k8s/k8s_daemonset_unused/__init__.py
unctl/checks/k8s/k8s_daemonset_unused/k8s_daemonset_unused.json
unctl/checks/k8s/k8s_daemonset_unused/k8s_daemonset_unused.py
unctl/checks/k8s/k8s_deployment_configmap_existence/k8s_deployment_configmap_existence.json
unctl/checks/k8s/k8s_deployment_configmap_existence/k8s_deployment_configmap_existence.py
unctl/checks/k8s/k8s_deployment_insufficient_replicas/__init__.py
unctl/checks/k8s/k8s_deployment_insufficient_replicas/k8s_deployment_insufficient_replicas.json
unctl/checks/k8s/k8s_deployment_insufficient_replicas/k8s_deployment_insufficient_replicas.py
unctl-1.0.3.dist-info/METADATA
unctl-1.0.3.dist-info/WHEEL
unctl-1.0.3.dist-info/entry_points.txt
unctl-1.0.3.dist-info/RECORD
